inmanta_plugins/git_ops/__init__.py
inmanta_plugins/git_ops/const.py
inmanta_plugins/git_ops/generator.py
inmanta_plugins/git_ops/processors.py
inmanta_plugins/git_ops/py.typed
inmanta_plugins/git_ops/setup.cfg
inmanta_plugins/git_ops/slice.py
inmanta_plugins/git_ops/store.py
inmanta_plugins/git_ops/files/.gitkeep
inmanta_plugins/git_ops/model/_init.cf
inmanta_plugins/git_ops/model/processors.cf
inmanta_plugins/git_ops/model/slice/_init.cf
inmanta_plugins/git_ops/templates/.gitkeep
inmanta_module_git_ops-0.1.4.dist-info/METADATA
inmanta_module_git_ops-0.1.4.dist-info/WHEEL
inmanta_module_git_ops-0.1.4.dist-info/top_level.txt
inmanta_module_git_ops-0.1.4.dist-info/RECORD
