Metadata-Version: 2.4
Name: inmanta-module-git-ops
Version: 0.1.4
Summary: Declarative parametrization, extension and validation of Inmanta DSL models.
Author: Guillaume Everarts de Velp
Author-email: edvgui@gmail.com
License: ASL 2.0
Project-URL: Source, https://github.com/edvgui/inmanta-module-git-ops
Project-URL: Changelog, https://github.com/edvgui/inmanta-module-git-ops/blob/master/CHANGELOG.md
Requires-Python: >=3.12
Requires-Dist: inmanta-module-std
Requires-Dist: inmanta-module-config
Requires-Dist: pydantic
Provides-Extra: generator
Requires-Dist: inmanta-module-factory<4,>=3.1; extra == "generator"
